AUTHORS
LICENSE
MANIFEST.in
README.md
setup.py
bangoo/__init__.py
bangoo/decorators.py
bangoo.egg-info/PKG-INFO
bangoo.egg-info/SOURCES.txt
bangoo.egg-info/dependency_links.txt
bangoo.egg-info/entry_points.txt
bangoo.egg-info/namespace_packages.txt
bangoo.egg-info/not-zip-safe
bangoo.egg-info/requires.txt
bangoo.egg-info/top_level.txt
bangoo/admin/__init__.py
bangoo/admin/api.py
bangoo/admin/models.py
bangoo/admin/tests.py
bangoo/admin/urls.py
bangoo/admin/static/admin/css/bootstrap-notify.css
bangoo/admin/static/admin/css/bootstrap.css
bangoo/admin/static/admin/css/common.css
bangoo/admin/static/admin/css/font-awesome.min.css
bangoo/admin/static/admin/css/jquery-ui.min.css
bangoo/admin/static/admin/css/multi-select.css
bangoo/admin/static/admin/css/simple-sidebar.css
bangoo/admin/static/admin/css/table.css
bangoo/admin/static/admin/css/images/animated-overlay.gif
bangoo/admin/static/admin/css/images/ui-bg_flat_0_aaaaaa_40x100.png
bangoo/admin/static/admin/css/images/ui-bg_flat_75_ffffff_40x100.png
bangoo/admin/static/admin/css/images/ui-bg_glass_55_fbf9ee_1x400.png
bangoo/admin/static/admin/css/images/ui-bg_glass_65_ffffff_1x400.png
bangoo/admin/static/admin/css/images/ui-bg_glass_75_dadada_1x400.png
bangoo/admin/static/admin/css/images/ui-bg_glass_75_e6e6e6_1x400.png
bangoo/admin/static/admin/css/images/ui-bg_glass_95_fef1ec_1x400.png
bangoo/admin/static/admin/css/images/ui-bg_highlight-soft_75_cccccc_1x100.png
bangoo/admin/static/admin/css/images/ui-icons_222222_256x240.png
bangoo/admin/static/admin/css/images/ui-icons_2e83ff_256x240.png
bangoo/admin/static/admin/css/images/ui-icons_454545_256x240.png
bangoo/admin/static/admin/css/images/ui-icons_888888_256x240.png
bangoo/admin/static/admin/css/images/ui-icons_cd0a0a_256x240.png
bangoo/admin/static/admin/fonts/FontAwesome.otf
bangoo/admin/static/admin/fonts/fontawesome-webfont.eot
bangoo/admin/static/admin/fonts/fontawesome-webfont.svg
bangoo/admin/static/admin/fonts/fontawesome-webfont.ttf
bangoo/admin/static/admin/fonts/fontawesome-webfont.woff
bangoo/admin/static/admin/fonts/fontawesome-webfont.woff2
bangoo/admin/static/admin/fonts/glyphicons-halflings-regular.eot
bangoo/admin/static/admin/fonts/glyphicons-halflings-regular.svg
